HadoopBijiPennywong/README.md
HadoopBijiPennywong/__init__.py
HadoopBijiPennywong/__main__.py
HadoopBijiPennywong/file.epub
HadoopBijiPennywong/index.html
HadoopBijiPennywong/css/__init__.py
HadoopBijiPennywong/css/annotations.css
HadoopBijiPennywong/css/main.css
HadoopBijiPennywong/css/normalize.css
HadoopBijiPennywong/css/popup.css
HadoopBijiPennywong/font/__init__.py
HadoopBijiPennywong/font/fontello.eot
HadoopBijiPennywong/font/fontello.svg
HadoopBijiPennywong/font/fontello.ttf
HadoopBijiPennywong/font/fontello.woff
HadoopBijiPennywong/img/__init__.py
HadoopBijiPennywong/img/annotator-glyph-sprite.png
HadoopBijiPennywong/img/annotator-icon-sprite.png
HadoopBijiPennywong/img/apple-touch-icon.png
HadoopBijiPennywong/img/cancelfullscreen.png
HadoopBijiPennywong/img/close.png
HadoopBijiPennywong/img/fullscreen.png
HadoopBijiPennywong/img/loader.gif
HadoopBijiPennywong/img/menu-icon.png
HadoopBijiPennywong/img/save.png
HadoopBijiPennywong/img/saved.png
HadoopBijiPennywong/img/settings-s.png
HadoopBijiPennywong/img/settings.png
HadoopBijiPennywong/img/star.png
HadoopBijiPennywong/js/__init__.py
HadoopBijiPennywong/js/epub.js
HadoopBijiPennywong/js/epub.min.js
HadoopBijiPennywong/js/epub.min.map
HadoopBijiPennywong/js/hooks.min.js
HadoopBijiPennywong/js/hooks.min.map
HadoopBijiPennywong/js/reader.js
HadoopBijiPennywong/js/reader.js.map
HadoopBijiPennywong/js/reader.min.js
HadoopBijiPennywong/js/reader.min.map
HadoopBijiPennywong/js/hooks/__init__.py
HadoopBijiPennywong/js/hooks/extensions/__init__.py
HadoopBijiPennywong/js/hooks/extensions/highlight.js
HadoopBijiPennywong/js/libs/__init__.py
HadoopBijiPennywong/js/libs/jquery.min.js
HadoopBijiPennywong/js/libs/localforage.min.js
HadoopBijiPennywong/js/libs/screenfull.js
HadoopBijiPennywong/js/libs/screenfull.min.js
HadoopBijiPennywong/js/libs/zip.min.js
HadoopBijiPennywong/js/plugins/__init__.py
HadoopBijiPennywong/js/plugins/hypothesis.js
HadoopBijiPennywong/js/plugins/search.js
hadoop_biji_pennywong-2024.3.2.0.dist-info/METADATA
hadoop_biji_pennywong-2024.3.2.0.dist-info/WHEEL
hadoop_biji_pennywong-2024.3.2.0.dist-info/entry_points.txt
hadoop_biji_pennywong-2024.3.2.0.dist-info/top_level.txt
hadoop_biji_pennywong-2024.3.2.0.dist-info/RECORD
